liquidcounter
