Metadata-Version: 1.0
Name: liquidcounter
Version: 1.0
Summary: Counter of votes for liquid democracy
Home-page: http://github.com/daviortega/liquidcounter
Author: Davi Ortega
Author-email: davi.ortega@gmail.com
License: CC0
Platform: UNKNOWN
